{"level":[[0],[0],[0],[2,1],[2,1],[2],[2,3],[6,5,4,3],[7],[0],[2,1],[2,1],[2],[2],[6,10,9,8,12,11],[6,10,9,8,12,11],[2],[2,13],[2,1],[2],[2],[6,10,9,8,12,11],[6,10,9,8,12,11],[2],[2],[2,3],[2,4],[2,4],[6,10,9,8,12,11],[6,10,9,8,12,11],[2],[2],[2],[2],[6,10,9,8,12,11],[6,14,4],[6,15,10,4,3],[2],[2],[2],[2],[6,10,9,8,12,11],[6,10,9,8,12,11],[2],[2],[0],[2,4],[2],[6,10,9,8,12,11],[6,10,9,8,12,11],[2],[2],[2],[2],[3],[6,16,10,4,3,7],[6,10,9,8,12,11],[2],[2],[2],[2],[2,3],[2,4],[0],[0],[2],[2],[2],[2],[2],[6,10,9,8],[6,17,4,3],[0],[0],[2],[2,4],[2],[6,10,9,8],[6,10,9,8],[2,18],[2,18],[0],[0],[2,3],[6,19,10,4,3,7],[6,10,9,8],[2,18],[2,18],[0],[0]],"metadata":{"editor_version":"2.19.5","game":"BlossomBlastSaga","level_hash":"8b17ea1442a53cf63b6fa6ad0e4a5a59","tracking_id":82450315},"properties":{"game_mode":"SPRING_CLEANING","is_hard":false,"nr_colors":"4","nr_moves":"20","random_seed":"0","star_1":"8000","star_2":"67510","star_3":"82100","tutorial_ids":""},"tiles":[{"max_start_strength":"4","min_start_strength":"3","type":"bud_spawner"},{"type":"normal_slot"},{"location":"east","type":"wall","wall_type":"wall"},{"location":"south","type":"wall","wall_type":"wall"},{"teleport_id":"1","type":"teleport_in"},{"type":"water_slot"},{"location":"west","type":"wall","wall_type":"wall"},{"health":"3","type":"weed"},{"type":"floating_log"},{"direction":"ne","type":"stream"},{"health":"3","location":"east","type":"wall","wall_type":"fence"},{"health":"3","location":"south","type":"wall","wall_type":"fence"},{"max_start_strength":"4","min_start_strength":"2","type":"bud_spawner"},{"teleport_id":"2","type":"teleport_in"},{"skin":"water","teleport_id":"3","type":"teleport_out"},{"skin":"water","teleport_id":"1","type":"teleport_out"},{"teleport_id":"3","type":"teleport_in"},{"health":"2","type":"weed"},{"skin":"water","teleport_id":"2","type":"teleport_out"}]}