{"level":[[1],[2,3],[1],[2],[2,3],[2],[1],[2,3],[1],[1],[2],[2],[2],[2],[2],[2],[2],[1],[2,4],[2],[2],[2],[2,5],[2],[2],[2],[2,4],[2,6],[2],[2],[2,6],[2,6],[2,6],[2],[2],[2,6],[2],[2],[2],[2,7],[2,7],[2,7],[2],[2],[2],[2,9,8],[2,8,11,10],[2,12,8],[2,12,8,11,10],[2,13,8],[2,12,8,11,10],[2,12,8],[2,8,11,10],[2,14,8],[1],[1],[2,15],[2,16],[2,12],[2,16],[2,17],[1],[1],[1],[2],[2],[2],[2,16],[2],[2],[2],[1],[1],[1],[2],[2],[2,18],[2],[2],[1],[1],[1],[1],[1],[1],[2,4],[1],[1],[1],[1]],"metadata":{"editor_version":"2.20.0","game":"BlossomBlastSaga","level_hash":"573141edb32cec9222529b617b20a2cd"},"properties":{"game_mode":"REMOVE_ALL_BIG_BUDS","is_hard":false,"nr_colors":"4","nr_moves":"17","random_seed":"0","star_1":"8000","star_2":"32000","star_3":"52000","tutorial_ids":""},"tiles":[{"type":"water_slot"},{"type":"normal_slot"},{"max_start_strength":"2","min_start_strength":"1","type":"bud_spawner"},{"max_strength":"10","type":"big_bud"},{"strength":"3","type":"honey_bee"},{"size":"1","type":"pile_of_leaves"},{"max_strength":"38","type":"big_bud"},{"location":"south","type":"wall","wall_type":"wall"},{"teleport_id":"1","type":"teleport_land_in"},{"location":"west","type":"wall","wall_type":"wall"},{"location":"east","type":"wall","wall_type":"wall"},{"max_strength":"25","type":"big_bud"},{"max_strength":"30","type":"big_bud"},{"teleport_id":"2","type":"teleport_land_in"},{"teleport_id":"2","type":"teleport_land_out"},{"max_strength":"15","type":"big_bud"},{"teleport_id":"1","type":"teleport_land_out"},{"type":"snail"}]}