{"level":[[2,1],[3,5,6,4],[2,7],[2],[2,7],[2],[2,7],[3,9,6,8],[2,1,10],[3,9,6,8],[2,4,10],[3,11,6,4,10],[3,11,6,4,10],[2],[2,4],[3,12,6],[3,9,6,8],[2,10],[3,9,6],[2],[2,4,10],[2,8,10],[3,11,6,8,10],[2,8,10],[3,13,6,10],[3,9,6,8],[2,10],[3,9,6],[2],[2,14,8],[2,8,10],[3,13,6,8,10],[2,8,10],[3,13,6,10],[3,9,6,8],[2,10],[3,9,6],[2],[2,8],[2,8,10],[3,13,6,8,10],[2,8,10],[3,13,6,10],[3,9,6,8],[2,10],[3,9,6],[2],[2,8],[2,8,10],[3,13,6,8,10],[2,8,10],[3,13,6,10],[3,9,6,8],[2,10],[3,9,6],[2],[2,8],[2,8,10],[3,13,6,8,10],[2,8,10],[3,13,6,10],[3,9,6,8],[2,10],[3,9,6],[2,4,8],[2,14,4,8],[2,4,8],[3,13,6,8,10],[2,4,8,10],[3,13,6,10],[3,9,6,8],[2,10],[3,9,6,8],[2,4,8,10],[2,4,8],[3,12,6],[3,13,6],[2],[3,13,6],[3,9,6,8],[2,10],[3,15,6],[3,12,6],[3,12,6],[2],[2],[2,16],[3,13,6],[3,11,6],[2,17,10]],"metadata":{"editor_version":"2.20.0","game":"BlossomBlastSaga","level_hash":"288e1bb185d04b691d18f52bf462ecbb"},"properties":{"game_mode":"COLLECT_FLOWERS","goal_1":"blue_9","goal_2":"orange_8","goal_3":"pink_8","goal_4":"red_5","is_hard":false,"nr_colors":"4","nr_moves":"16","random_seed":"0","star_1":"8000","star_2":"20000","star_3":"34000","tutorial_ids":""},"tiles":[{"exclude_color":"2","max_start_strength":"3","min_start_strength":"1","type":"bud_spawner"},{"type":"normal_slot"},{"type":"water_slot"},{"health":"3","location":"south","type":"wall","wall_type":"fence"},{"direction":"sw","type":"stream"},{"type":"floating_log"},{"exclude_color":"4","max_start_strength":"2","min_start_strength":"1","type":"bud_spawner"},{"health":"3","location":"east","type":"wall","wall_type":"fence"},{"direction":"s","type":"stream"},{"health":"3","location":"west","type":"wall","wall_type":"fence"},{"direction":"nw","type":"stream"},{"direction":"ne","type":"stream"},{"direction":"n","type":"stream"},{"direction":"left","health":"3","type":"crow"},{"direction":"se","type":"stream"},{"direction":"right","health":"3","type":"crow"},{"direction":"up","health":"3","type":"crow"}]}