{"level":[[1],[2],[2,3],[2],[1],[2],[2,3],[2],[1],[1],[2],[2],[2],[2],[2],[2],[2],[1],[1],[2],[2],[2],[2,4],[2],[2],[2],[1],[2],[2],[2],[2],[2,5],[2],[2],[2],[2],[2,7,6],[2,4],[2],[2],[2,4],[2],[2],[2,4],[2,7,6],[2,8],[2],[2],[2],[2],[2],[2],[2],[2,8],[2,8],[2,9],[2,5],[2,8],[2,4],[2,8],[2,5],[2,9],[2,8],[2,7,6],[2],[2],[2,10,11,6],[2,10,6],[2,10,12,6],[2],[2],[2,7,6],[2],[2,6],[2,11,6],[2,10,12,6],[2,13],[2,10,11,6],[2,12,6],[2,6],[2],[1],[1],[2],[1],[2,10,11,12,6],[1],[2],[1],[1]],"metadata":{"editor_version":"2.20.0","game":"BlossomBlastSaga","level_hash":"8343b2bbba0b41e3dfdcad35ea916359"},"properties":{"game_mode":"COLLECT_FLOWERS","goal_1":"blue_7","goal_2":"pink_7","goal_3":"orange_7","goal_4":"red_7","goal_5":"pink_7","is_hard":false,"nr_colors":"4","nr_moves":"13","random_seed":"0","star_1":"8000","star_2":"27000","star_3":"46000","tutorial_ids":""},"tiles":[{"type":"water_slot"},{"type":"normal_slot"},{"exclude_color":"4","max_start_strength":"2","min_start_strength":"1","type":"bud_spawner"},{"health":"2","type":"pot"},{"health":"2","level":"2","type":"water_bucket"},{"health":"3","type":"slime"},{"color":"4","strength":"1","type":"bud"},{"size":"1","type":"pile_of_leaves"},{"health":"1","type":"pot"},{"location":"south","type":"wall","wall_type":"wall"},{"location":"east","type":"wall","wall_type":"wall"},{"location":"west","type":"wall","wall_type":"wall"},{"color":"4","max_start_strength":"2","min_start_strength":"1","type":"bud_spawner"}]}