{"level":[[2,1,3],[2,3,4],[6,5],[6],[6,7],[6],[6,8],[6],[6,5],[6,9,10],[6,11],[2,3,4,9,10],[2,3,4],[6],[6],[6],[6],[6],[6,12],[6],[6],[6],[2,13],[6],[6],[2,14,4,9,10],[2,15,14],[6,12],[6],[6],[6],[6],[2,14,4],[2,14,4],[6,11],[6,9,10],[6,9,10],[6,11],[6],[2,16],[2,14,4,9,10],[6],[6],[6],[6,9],[2,17,3],[2,3,4],[6],[6],[6],[6],[6],[6],[6,12],[6,9],[6],[2,3,4,9,10],[2,3,4],[6],[6],[6],[6,11],[6,9,10],[6,9],[6],[6],[6],[2,18],[6],[6],[2,14,4,9,10],[2,19,14],[6,9],[6],[6],[6],[6],[2,14,4],[2,14,4],[6],[6,9,10],[6,9],[6,20],[6],[2,21],[2,14,4,9,10],[6,9,10],[6],[6,9,10],[6,9,10]],"metadata":{"editor_version":"2.20.0","game":"BlossomBlastSaga","level_hash":"0810e5e4234f6163a54aa2f06c42c040"},"properties":{"game_mode":"SPRING_CLEANING","is_hard":false,"nr_colors":"4","nr_moves":"22","random_seed":"0","star_1":"8000","star_2":"24500","star_3":"41000","tutorial_ids":""},"tiles":[{"skin":"water","teleport_id":"4","type":"teleport_out"},{"type":"water_slot"},{"direction":"se","type":"stream"},{"type":"floating_log"},{"exclude_color":"2","max_start_strength":"2","min_start_strength":"1","type":"bud_spawner"},{"type":"normal_slot"},{"max_start_strength":"3","min_start_strength":"1","type":"bud_spawner"},{"max_start_strength":"2","min_start_strength":"1","type":"bud_spawner"},{"health":"1","type":"weed"},{"health":"3","type":"slime"},{"health":"2","level":"2","type":"water_bucket"},{"health":"2","type":"weed"},{"skin":"water","teleport_id":"1","type":"teleport_in"},{"direction":"sw","type":"stream"},{"skin":"water","teleport_id":"1","type":"teleport_out"},{"skin":"water","teleport_id":"2","type":"teleport_in"},{"skin":"water","teleport_id":"2","type":"teleport_out"},{"skin":"water","teleport_id":"3","type":"teleport_in"},{"skin":"water","teleport_id":"3","type":"teleport_out"},{"type":"snail"},{"skin":"water","teleport_id":"4","type":"teleport_in"}]}