{"level":[[0],[0],[0],[0],[0],[0],[0],[0],[0],[0],[0],[0],[1,2],[0],[3,5,4],[0],[1,2],[0],[0],[1,6],[1],[1],[3,8,7],[1],[1],[1],[0],[0],[1],[1,6],[1,6],[3,8,7],[1],[1,6],[1],[3,9,8],[0],[1],[1],[1],[3,8,7],[1,10],[1],[3,4,7],[3,4,7],[1,10],[1],[1],[3,8,7],[3,4],[3,8],[3,4,7],[1],[1],[1,11],[0],[3],[3,12],[1,13],[3,4,7],[1,6],[1,6],[1],[0],[0],[0],[0],[3,14],[3],[1],[1],[1,6],[0],[0],[0],[0],[0],[1,10],[1],[1],[1],[0],[0],[0],[0],[0],[1,11],[1],[0],[0]],"metadata":{"editor_version":"2.20.0","game":"BlossomBlastSaga","level_hash":"57535d04314d0a870c788b649aed7ba8"},"properties":{"game_mode":"COLLECT_FLOWERS","goal_1":"7","goal_2":"7","goal_3":"7","goal_4":"7","is_hard":false,"nr_colors":"4","nr_moves":"15","random_seed":"0","star_1":"8000","star_2":"22500","star_3":"37000","tutorial_ids":""},"tiles":[{"type":"normal_slot"},{"max_start_strength":"3","min_start_strength":"1","type":"bud_spawner"},{"type":"water_slot"},{"direction":"sw","type":"stream"},{"skin":"water","teleport_id":"2","type":"teleport_out"},{"health":"3","type":"green_house"},{"type":"floating_log"},{"direction":"s","type":"stream"},{"skin":"water","teleport_id":"1","type":"teleport_out"},{"health":"3","type":"slime"},{"direction":"right","health":"3","type":"crow"},{"skin":"water","teleport_id":"1","type":"teleport_in"},{"direction":"up","health":"3","type":"crow"},{"skin":"water","teleport_id":"2","type":"teleport_in"}]}