{"level":[[2,3,1],[2,1,4],[2,5],[2,3,1,6],[2,7,6,4],[2,3,1,4],[2,8],[2,1,6],[2,3,1],[2],[2],[2],[2],[2,9,1,6,4],[2],[2],[2],[2],[2],[2],[2],[2],[2],[2],[2],[2],[2],[2],[2],[2],[2,6],[2,1],[2,4],[2],[2],[2],[2,10],[2],[2],[2,11],[2,12,13,6,4],[2,14],[2],[2],[2,10],[2],[2],[2],[2,15,6],[2,16,6,4],[2,15,4],[2],[2],[2],[2],[2],[2],[2,15,6],[2,17,6,4],[2,15,4],[2],[2],[2],[2,18],[2],[2],[2,15,6],[2,16,6,4],[2,15,4],[2],[2],[2,18],[2],[2],[2],[2,1,6],[2,21,6,4,19,20],[2,1,4],[2],[2],[2],[2],[2],[2,6],[2,22],[2,17],[2,23],[2,4],[2],[2]],"metadata":{"editor_version":"2.19.5","game":"BlossomBlastSaga","level_hash":"015c1af3e8aa09c7045c61464aa04c16","tracking_id":52059137},"properties":{"game_mode":"REMOVE_ALL_BIG_BUDS","is_hard":true,"nr_colors":"4","nr_moves":"19","random_seed":"0","star_1":"8000","star_2":"88380","star_3":"108010","tutorial_ids":""},"tiles":[{"location":"south","type":"wall","wall_type":"wall"},{"type":"normal_slot"},{"max_start_strength":"2","min_start_strength":"1","type":"bud_spawner"},{"location":"west","type":"wall","wall_type":"wall"},{"teleport_id":"2","type":"teleport_land_out"},{"location":"east","type":"wall","wall_type":"wall"},{"max_start_strength":"5","min_start_strength":"3","type":"bud_spawner"},{"teleport_id":"3","type":"teleport_land_out"},{"teleport_id":"1","type":"teleport_land_in"},{"max_strength":"45","type":"big_bud"},{"health":"3","location":"east","type":"wall","wall_type":"fence"},{"teleport_id":"1","type":"teleport_land_out"},{"health":"3","location":"south","type":"wall","wall_type":"fence"},{"health":"3","location":"west","type":"wall","wall_type":"fence"},{"max_strength":"10","type":"big_bud"},{"type":"snail"},{"health":"2","type":"pot"},{"max_strength":"40","type":"big_bud"},{"health":"3","type":"slime"},{"health":"3","type":"green_house"},{"health":"3","type":"pot"},{"teleport_id":"2","type":"teleport_land_in"},{"teleport_id":"3","type":"teleport_land_in"}]}