{"level":[[0],[2,1],[0],[2],[2,1],[2],[0],[2,1],[0],[0],[2],[2],[2],[2],[2],[2],[2],[0],[2],[2],[5,4,3],[2],[2],[2],[5,4,3],[2],[2],[2,6],[5,4,3],[2],[2],[2],[2],[2],[5,4,3],[2,6],[2,7],[2],[2,8],[2,9],[2,10],[2,11],[2,8],[2],[2,7],[2,12],[2],[2],[2],[2,13],[2],[2],[2],[2,12],[5,4,3],[2,7],[2],[2],[2,7],[2],[2],[2,7],[5,4,3],[2,14],[5,4,3],[2],[2,11],[2,10],[2,9],[2],[5,4,3],[2,14],[0],[2],[2,15],[2],[2,7],[2],[2,15],[2],[0],[2,16],[0],[2],[2],[2,17],[2],[2],[0],[2,16]],"metadata":{"editor_version":"2.20.3","game":"BlossomBlastSaga","level_hash":"aef6bcf12cd24a464e79a4a99eb962e6"},"properties":{"game_mode":"REMOVE_ALL_BIG_BUDS","is_hard":false,"nr_colors":"4","nr_moves":"15","random_seed":"0","star_1":"8000","star_2":"34500","star_3":"61000","tutorial_ids":""},"tiles":[{"max_start_strength":"2","min_start_strength":"1","type":"bud_spawner"},{"type":"normal_slot"},{"type":"water_lily_leaf_spawner"},{"type":"water_lily_leaf"},{"type":"water_slot"},{"max_strength":"17","type":"big_bud"},{"type":"exploding_mushroom"},{"max_strength":"8","type":"big_bud"},{"health":"1","level":"1","type":"water_bucket"},{"strength":"3","type":"honey_bee"},{"health":"2","level":"2","type":"water_bucket"},{"max_strength":"19","type":"big_bud"},{"max_strength":"33","type":"big_bud"},{"max_strength":"21","type":"big_bud"},{"max_strength":"16","type":"big_bud"},{"max_strength":"4","type":"big_bud"},{"max_strength":"36","type":"big_bud"}]}