{"level":[[0],[0],[2,1],[2],[0],[2],[2,1],[0],[0],[2,3],[2],[0],[6,5,4],[2],[6,5,4],[0],[2],[2,3],[6],[2],[6,5,4,7],[2,8],[2],[2,8],[6,5,4,7],[2],[6],[2],[6,5,9],[2,10],[2,8],[6,5,11],[2,8],[2,12],[6,5,9],[2],[2],[2],[2,13,8],[2,13],[2],[2,13],[2,13,8],[2],[2],[6],[2,8],[2],[6,5,4,13],[2,14,13],[6,5,4,13],[2],[2,8],[6],[2,8],[6,5,15],[6,5,4,13],[2],[6,5,16,13],[2],[6,5,4,13],[6,5,15],[2,8],[2,8],[2],[2],[2],[2],[2],[2],[2],[2,8],[2,12],[6,5,4,11],[6,5,4,11],[2],[2,14],[2],[6,5,4,11],[6,5,4,11],[2,10],[0],[0],[2],[2],[6,5,4,16],[2],[2],[0],[0]],"metadata":{"editor_version":"2.20.0","game":"BlossomBlastSaga","level_hash":"397b01a968b29cddca6841a870fea151"},"properties":{"game_mode":"REMOVE_ALL_BIG_BUDS","is_hard":false,"nr_colors":"4","nr_moves":"20","random_seed":"0","star_1":"8000","star_2":"29000","star_3":"51000","tutorial_ids":""},"tiles":[{"max_start_strength":"2","min_start_strength":"1","type":"bud_spawner"},{"type":"normal_slot"},{"max_start_strength":"3","min_start_strength":"1","type":"bud_spawner"},{"type":"water_lily_leaf_spawner"},{"type":"water_lily_leaf"},{"type":"water_slot"},{"max_strength":"8","type":"big_bud"},{"health":"3","type":"green_house"},{"max_strength":"16","type":"big_bud"},{"direction":"left","health":"3","type":"crow"},{"max_strength":"24","type":"big_bud"},{"direction":"right","health":"3","type":"crow"},{"health":"3","location":"south","type":"wall","wall_type":"fence"},{"direction":"up","health":"3","type":"crow"},{"max_strength":"32","type":"big_bud"},{"max_strength":"46","type":"big_bud"}]}