{"level":[[0],[1],[1,2],[1],[0],[1],[1,2],[1],[0],[1],[3,4],[1],[1],[1],[1],[1],[3,4],[1],[1,5],[3,7,4,6],[1],[1],[3,7,4,8],[1],[1],[3,7,4,6],[1,5],[0],[3,4],[1],[1],[1],[1],[1],[3,4],[0],[0],[1,9],[1,10],[1],[1],[1],[1,11],[1,9],[0],[1,5],[1,9],[1,12],[1],[3,7,4,6],[1],[1,12],[1,9],[1,5],[0],[3,7,4,8],[1,13],[1],[1],[1],[1,13],[3,7,4,8],[0],[1,5],[1,5],[3,7,4,8],[1,14],[1],[1,14],[3,7,4,8],[1,5],[1,5],[0],[0],[1],[1],[1,14],[1],[1],[0],[0],[0],[0],[1,10],[3,7,4,5],[3,7,4,5],[3,7,4,5],[1,11],[0],[0]],"metadata":{"editor_version":"2.20.0","game":"BlossomBlastSaga","level_hash":"20f9bf66e58567a57945c3750e5b7961"},"properties":{"game_mode":"SPRING_CLEANING","is_hard":false,"nr_colors":"4","nr_moves":"19","random_seed":"0","star_1":"8000","star_2":"17000","star_3":"27000","tutorial_ids":""},"tiles":[{"type":"normal_slot"},{"max_start_strength":"2","min_start_strength":"1","type":"bud_spawner"},{"type":"water_slot"},{"type":"water_lily_leaf_spawner"},{"health":"2","type":"weed"},{"type":"exploding_mushroom"},{"type":"water_lily_leaf"},{"health":"1","type":"pot"},{"health":"3","type":"weed"},{"direction":"right","health":"3","type":"crow"},{"direction":"left","health":"3","type":"crow"},{"health":"1","type":"rolling_stone"},{"direction":"up","health":"3","type":"crow"},{"health":"2","type":"pot"}]}