{"level":[[0],[0],[2,1],[2],[2,1],[2],[2,1],[0],[0],[0],[2],[2],[2],[3,4],[2],[2],[2],[0],[2,1],[2],[2,5],[2],[3,7,8,6],[2],[2,5],[2],[2,1],[0],[2],[2],[2],[3,7,8,6],[2],[2],[2],[0],[2],[2,6],[2],[2],[3,7,8,9],[2],[2],[2,6],[2],[2],[2],[2],[2],[3,7,8,6],[2],[2],[2],[2],[2],[2,5],[2],[2],[3,7,8,6],[2],[2],[2,5],[2],[2],[2],[2],[2],[3,7,8,6],[2],[2],[2],[2],[0],[2],[2],[2,10],[3,7,8,6],[2,10],[2],[2],[0],[0],[0],[2],[2],[3,11,7],[2],[2],[0],[0]],"metadata":{"editor_version":"2.19.5","game":"BlossomBlastSaga","level_hash":"0a86d4faab166621b43797cee089545d","tracking_id":181700106},"properties":{"game_mode":"REMOVE_ALL_BIG_BUDS","is_hard":true,"nr_colors":"4","nr_moves":"20","random_seed":"0","star_1":"8000","star_2":"44080","star_3":"54640","tutorial_ids":""},"tiles":[{"max_start_strength":"2","min_start_strength":"1","type":"bud_spawner"},{"type":"normal_slot"},{"type":"water_slot"},{"teleport_id":"1","type":"teleport_in"},{"max_strength":"20","type":"big_bud"},{"health":"3","level":"3","type":"water_bucket"},{"direction":"n","type":"stream"},{"type":"floating_log"},{"color":"4","max_strength":"60","type":"big_bud"},{"max_strength":"25","type":"big_bud"},{"skin":"water","teleport_id":"1","type":"teleport_out"}]}