{"level":[[2,1],[2,1],[2,1],[2,1],[2,5,3,4],[2,1],[2,1],[2,1],[2,1],[2],[2],[2],[2],[2,3,4],[2],[2],[2],[2],[2],[2,6],[2],[2],[2,3,4],[2],[2],[2,6],[2],[2,7],[2],[2],[2,8],[2,3,4],[2,8],[2],[2],[2,7],[2],[2],[2,3],[2],[2],[2],[2,4],[2],[2],[2,7],[2,3],[2,8],[2],[2,9],[2],[2,8],[2,4],[2,7],[2],[2,8],[2],[2],[2,7],[2],[2],[2,8],[2],[2,3],[2],[2],[2,6],[2,7],[2,6],[2],[2],[2,4],[2],[2,10,6],[2,11],[2,11,10,12],[2,7,11],[2,11,10,12],[2,11],[2,12,6],[2],[2,7],[2,9],[2,9],[2,7],[2,7],[2,7],[2,9],[2,9],[2,7]],"metadata":{"editor_version":"2.19.5","game":"BlossomBlastSaga","level_hash":"9351231cd71df8a56b82ba5da2babf9f","tracking_id":203641235},"properties":{"game_mode":"SPRING_CLEANING","is_hard":false,"nr_colors":"4","nr_moves":"18","random_seed":"0","star_1":"8000","star_2":"29210","star_3":"38490","tutorial_ids":""},"tiles":[{"max_start_strength":"3","min_start_strength":"2","type":"bud_spawner"},{"type":"normal_slot"},{"location":"east","type":"wall","wall_type":"wall"},{"location":"west","type":"wall","wall_type":"wall"},{"max_start_strength":"1","min_start_strength":"1","type":"bud_spawner"},{"size":"1","type":"pile_of_leaves"},{"health":"3","type":"weed"},{"location":"south","type":"wall","wall_type":"wall"},{"health":"2","type":"weed"},{"health":"3","location":"east","type":"wall","wall_type":"fence"},{"health":"3","location":"south","type":"wall","wall_type":"fence"},{"health":"3","location":"west","type":"wall","wall_type":"fence"}]}