{"level":[[1],[2],[2,3],[1],[2,4],[1],[2,3],[2],[1],[2],[2],[1],[2],[2,5,6],[2],[1],[2],[2],[2],[2,7],[2],[2],[2,5,6],[2],[2],[2,7],[2],[2,5],[2,8,7,5,6],[1,10,9,6],[1,10,9],[2,5,6],[1,10,9],[1,10,9,5],[2,8,7,5,6],[2,6],[1],[2],[2],[2,11,5],[2,12,7,5,6],[2,11,6],[2],[2],[1],[1],[2,7],[2],[2],[2,13,7,5,6],[2],[2],[2,7],[1],[2,14,5],[2,8,7,5,6],[1,10,9,6],[1,10,9],[2],[1,10,9],[1,10,9,5],[2,8,7,5,6],[2,15,6],[2],[2],[2],[2],[2],[2],[2],[2],[2],[2],[1],[2],[2,15],[2,12],[2,14],[2],[1],[2],[2],[2,15],[1],[2,16],[2,16],[2,16],[1],[2,14],[2]],"metadata":{"editor_version":"2.20.3","game":"BlossomBlastSaga","level_hash":"eb159c1e2c977deca26345fb58e73eab"},"properties":{"game_mode":"REACH_SCORE_TARGET","is_hard":false,"nr_colors":"3","nr_moves":"20","random_seed":"0","star_1":"29000","star_2":"39000","star_3":"45000","tutorial_ids":""},"tiles":[{"type":"water_slot"},{"type":"normal_slot"},{"exclude_color":"3","max_start_strength":"2","min_start_strength":"1","type":"bud_spawner"},{"exclude_color":"3","max_start_strength":"3","min_start_strength":"1","type":"bud_spawner"},{"health":"3","location":"east","type":"wall","wall_type":"fence"},{"health":"3","location":"west","type":"wall","wall_type":"fence"},{"health":"3","location":"south","type":"wall","wall_type":"fence"},{"health":"2","type":"falling_pot"},{"type":"water_lily_leaf_spawner"},{"type":"water_lily_leaf"},{"health":"3","type":"rolling_stone"},{"direction":"up","health":"3","type":"crow"},{"health":"3","type":"falling_pot"},{"direction":"right","health":"3","type":"crow"},{"direction":"left","health":"3","type":"crow"},{"health":"1","type":"falling_pot"}]}