{"level":[[0],[1,2,3],[4,5],[4],[0],[4],[4,5],[1,2,3],[0],[0],[1,6,3],[4],[4],[4],[4],[4],[1,6,3],[0],[4],[1,2,3,7],[4],[4],[4],[4],[4],[1,2,3,7],[4],[4],[1,6,3],[4],[1,8,3],[1,9,3,7],[1,9,3],[4],[1,6,3],[4],[4],[4],[1,8],[4],[4],[4],[1,2],[4],[4],[4],[4],[1,6,3],[4],[4],[4],[1,2,3],[4],[4],[4,10],[1,8,3,7],[1,6],[4],[4,10],[4],[1,9],[1,9,3,7],[4,10],[1,11,8],[4],[4],[4,14,13,12],[4,14,7],[4,14,15,12],[4],[4],[1,16],[4,17],[4,14,13,7],[4,14,13,7],[4,7],[4,18],[4,7],[4,14,15,7],[4,14,15,7],[4,17],[4,13,7],[4,19],[1,9,3,12],[1,20,3,12],[4,7],[1,8,3,12],[1,21,3,12],[4,19],[4,15,7]],"metadata":{"editor_version":"2.20.0","game":"BlossomBlastSaga","level_hash":"de5afb22def1e531e413be95fc53b860"},"properties":{"game_mode":"COLLECT_FLOWERS","goal_1":"red_7","goal_2":"orange_7","goal_3":"blue_7","goal_4":"pink_7","goal_5":"orange_7","is_hard":true,"nr_colors":"4","nr_moves":"17","random_seed":"0","star_1":"8000","star_2":"27000","star_3":"46000","tutorial_ids":""},"tiles":[{"type":"water_slot"},{"direction":"s","type":"stream"},{"type":"floating_log"},{"type":"normal_slot"},{"exclude_color":"3","max_start_strength":"2","min_start_strength":"1","type":"bud_spawner"},{"direction":"n","type":"stream"},{"health":"3","type":"slime"},{"direction":"ne","type":"stream"},{"direction":"se","type":"stream"},{"animate_at_creation":"0","health":"1","type":"molehill"},{"skin":"water","teleport_id":"1","type":"teleport_out"},{"size":"1","type":"pile_of_leaves"},{"health":"3","location":"east","type":"wall","wall_type":"fence"},{"location":"south","type":"wall","wall_type":"wall"},{"health":"3","location":"west","type":"wall","wall_type":"fence"},{"skin":"water","teleport_id":"1","type":"teleport_in"},{"animate_at_creation":"0","health":"2","type":"molehill"},{"exclude_color":"2","exclude_color2":"1","max_start_strength":"2","min_start_strength":"1","type":"bud_spawner"},{"color":"3","strength":"1","type":"bud"},{"direction":"nw","type":"stream"},{"direction":"sw","type":"stream"}]}