{"level":[[1,2],[1],[5,3,4],[5,3,4],[1,2],[5,3,4],[5,3,4],[1],[1,2],[1],[1],[1],[1],[1],[1],[1],[1],[1],[1],[5,3,7,4,6],[5,3,7,8],[1],[5,3,10,9],[1],[5,3,7,8],[5,3,7,4,6],[1],[5,3,7,10,6,11],[1],[1],[1],[5,3,10,9],[1],[1],[1],[5,3,7,10,6,12],[1,6],[1,12],[1],[1],[1],[1],[1],[1,11],[1,6],[5,3,8],[1,13,6,11],[1,6],[1,13,9],[1,13,6,9],[1,13,9],[1,6],[1,13,6,12],[5,3,8],[5,3,8],[5,3,7,8],[5,3,7,8],[1],[1,14,9],[1],[5,3,7,8],[5,3,7,8],[5,3,8],[5,3,7,8,6],[1],[1],[1,11],[1],[1,12],[1],[1],[5,3,7,8,6],[1,9],[1,9],[1,9],[1],[1,15,11,12],[1],[1,9],[1,9],[1,9],[0],[5,3,8],[1,9],[0],[0],[0],[1,9],[5,3,8],[0]],"metadata":{"editor_version":"2.20.0","game":"BlossomBlastSaga","level_hash":"b9a690564244ea41a4ad7a09958b3540"},"properties":{"game_mode":"SPRING_CLEANING","is_hard":true,"nr_colors":"3","nr_moves":"22","random_seed":"0","star_1":"8000","star_2":"30500","star_3":"53000","tutorial_ids":""},"tiles":[{"type":"normal_slot"},{"exclude_color":"3","max_start_strength":"2","min_start_strength":"1","type":"bud_spawner"},{"type":"water_lily_leaf"},{"health":"1","type":"weed"},{"type":"water_slot"},{"location":"south","type":"wall","wall_type":"wall"},{"type":"water_lily_leaf_spawner"},{"health":"3","type":"weed"},{"health":"3","type":"green_house"},{"health":"2","type":"weed"},{"location":"east","type":"wall","wall_type":"wall"},{"location":"west","type":"wall","wall_type":"wall"},{"health":"1","type":"pot"},{"health":"2","type":"pot"},{"animate_at_creation":"0","health":"3","type":"molehill"}]}