{"level":[[0],[0],[0],[3,1,2],[5,4],[3,1,2],[0],[0],[0],[3],[3,6],[3,1,2,7],[3,1,2,8],[3,1,2,9],[3,1,2,10],[3,1,2,6],[3,7],[3],[5,11],[5],[3,1,2,12,7],[3,1,2,12,7],[3,1,13,9,8,10,14],[3,1,2,12,6],[3,1,2,12,6],[5],[5,11],[5,9],[5,9,10],[5],[5],[3,1,2,12,6,7],[5],[5],[5,9,8],[5,9],[5,13,14],[5,15,14],[5,9,10],[5,10],[5],[5,8],[5,9,8],[5,15,14],[5,13,14],[5,13,14],[5,15,9,14],[5,13,9,8,14],[5],[5,13],[5],[5,13,9,10,14],[5,15,9,10,14],[5,13,14],[5,13,9,8,14],[5],[5,16],[5],[5],[5],[5,16],[5],[5,13,9,10,14],[5],[5],[5],[3],[3,1,2,14],[3],[5],[5],[5],[5],[3],[3],[0],[3,1,2,13],[0],[3],[3],[5],[3],[0],[0],[0],[5,17],[0],[0],[0],[3]],"metadata":{"editor_version":"2.20.0","game":"BlossomBlastSaga","level_hash":"874e75187c1e4af22470fdeba8930a34"},"properties":{"game_mode":"SPRING_CLEANING","is_hard":true,"nr_colors":"3","nr_moves":"20","random_seed":"0","star_1":"8000","star_2":"20000","star_3":"35000","tutorial_ids":""},"tiles":[{"type":"water_lily_leaf"},{"type":"water_lily_leaf_spawner"},{"type":"water_slot"},{"teleport_id":"1","type":"teleport_land_out"},{"type":"normal_slot"},{"location":"east","type":"wall","wall_type":"wall"},{"location":"west","type":"wall","wall_type":"wall"},{"health":"3","location":"east","type":"wall","wall_type":"fence"},{"health":"3","location":"south","type":"wall","wall_type":"fence"},{"health":"3","location":"west","type":"wall","wall_type":"fence"},{"exclude_color":"2","max_start_strength":"2","min_start_strength":"1","type":"bud_spawner"},{"location":"south","type":"wall","wall_type":"wall"},{"health":"3","type":"weed"},{"health":"3","type":"green_house"},{"health":"2","type":"weed"},{"health":"1","type":"rolling_stone"},{"teleport_id":"1","type":"teleport_land_in"}]}