{"level":[[1],[1],[1],[2,3],[1],[2,3],[1],[1],[1],[1],[1],[1,5,4],[2],[1,6,4],[2],[1,7,4],[1],[1],[1],[1],[1,4,8],[1],[1,4,8],[1],[1,4,8],[1],[1],[1],[2],[1,4,8],[1],[1,4,8],[1],[1,4,8],[2],[1],[2],[2],[1,4,8],[2],[1,4,8],[2],[1,4,8],[2],[2],[2],[2],[1,9,4],[2],[1,10,4],[2],[1,11,4],[2],[2],[2],[2,12,13],[2],[2,12,13],[2],[2,12,13],[2],[2,12,13],[2],[2,12,13],[2,13],[2,12,13],[2,13],[2,12,13],[2,13],[2,12,13],[2,13],[2,12,13],[2,13],[2,13],[2,13],[2,13],[2,13],[2,13],[2,13],[2,13],[2,13],[2,14,13],[2,14,13],[2,14,13],[2,14,13],[2,14,13],[2,14,13],[2,14,13],[2,14,13],[2,14,13]],"metadata":{"editor_version":"2.20.0","game":"BlossomBlastSaga","level_hash":"dd30f1807fc5745d4890f0f78762ada6"},"properties":{"game_mode":"REACH_SCORE_TARGET","is_hard":false,"nr_colors":"4","nr_moves":"16","random_seed":"0","star_1":"23000","star_2":"26000","star_3":"30000","tutorial_ids":""},"tiles":[{"type":"water_slot"},{"type":"normal_slot"},{"max_start_strength":"2","min_start_strength":"1","type":"bud_spawner"},{"direction":"s","type":"stream"},{"skin":"water","teleport_id":"1","type":"teleport_out"},{"skin":"water","teleport_id":"2","type":"teleport_out"},{"skin":"water","teleport_id":"3","type":"teleport_out"},{"type":"floating_log"},{"skin":"water","teleport_id":"1","type":"teleport_in"},{"skin":"water","teleport_id":"2","type":"teleport_in"},{"skin":"water","teleport_id":"3","type":"teleport_in"},{"health":"3","type":"rolling_stone"},{"size":"1","type":"pile_of_leaves"},{"animate_at_creation":"0","health":"3","type":"molehill"}]}