{"level":[[2,1],[2],[2,3],[2],[2,1],[2],[2,3],[2],[2,1],[2],[2,5,4,6],[2,5,6],[2,7],[2],[2,4],[2,5,6],[2,5,7,6],[2],[2,4],[2,8,5,4,7],[2,8,5,4],[2],[2],[2],[2,8,5,7],[2,8,5,4,7],[2,7],[2],[2,4,6],[2,5,6],[2,5,7],[2],[2,5,4],[2,5,6],[2,7,6],[2],[2],[2,6],[2,8,5,7],[2,8,5,4,7],[2,4,7],[2,8,5,4,7],[2,8,5,4],[2,6],[2],[2],[2],[2,6],[2],[2],[2],[2,6],[2],[2],[2,8,6],[2],[2,9,6],[2],[2,9,6],[2],[2,9,6],[2],[2,8,6],[2,10],[2,9,6],[2,10],[2,8,6],[2,10],[2,8,6],[2,10],[2,9,6],[2,10],[2,11],[2,11],[2,11],[2,11],[2,11],[2,11],[2,11],[2,11],[2,11],[2,9,10],[2,9,10],[2,9,10],[2,9,10],[2,9,10],[2,9,10],[2,9,10],[2,9,10],[2,9,10]],"metadata":{"editor_version":"2.20.0","game":"BlossomBlastSaga","level_hash":"b8c88f1475eb6f4022db092389d90094"},"properties":{"game_mode":"SPRING_CLEANING","is_hard":false,"nr_colors":"4","nr_moves":"18","random_seed":"0","star_1":"8000","star_2":"34000","star_3":"61000","tutorial_ids":""},"tiles":[{"max_start_strength":"2","min_start_strength":"1","type":"bud_spawner"},{"type":"normal_slot"},{"max_start_strength":"3","min_start_strength":"1","type":"bud_spawner"},{"health":"3","location":"east","type":"wall","wall_type":"fence"},{"health":"3","location":"south","type":"wall","wall_type":"fence"},{"health":"3","type":"green_house"},{"health":"3","location":"west","type":"wall","wall_type":"fence"},{"health":"3","type":"weed"},{"health":"2","type":"weed"},{"size":"1","type":"pile_of_leaves"},{"max_start_strength":"2","min_start_strength":"1","type":"bud"}]}