{"level":[[2,1],[2],[0],[2,3],[2,4],[2,5],[0],[2],[2,1],[0],[2,3],[2,5],[2,6,3],[2],[2,6,5],[2,3],[2,5],[0],[2,7,5,8],[2,3],[11,9,10],[11,9,10,7,5],[2,5,3],[11,9,10,7,3],[11,9,10],[2,5],[2,7,3,8],[2,7,5,8],[2],[2,12],[11,9,10,7,5],[2,5,3],[11,9,10,7,3],[2,13],[2],[2,7,3,8],[0],[2],[2],[11,9,10,5],[2,5,3],[11,9,10,3],[2],[2],[0],[0],[2],[2],[11,9,10,5],[2,5,3],[11,9,10,3],[2],[2],[0],[0],[2],[2],[11,9,10,7,5],[2,5,3],[11,9,10,7,3],[2],[2],[0],[2,6],[2,6,3],[2,12],[11,9,10,7,5],[2,5,3],[11,9,10,7,3],[2,13],[2,6,5],[2,6],[2,8],[2,8],[11,9,10,3],[6,5],[2,14,5,3],[6,3],[11,9,10,5],[2,8],[2,8],[2,7,8],[0],[0],[2,7],[2,15],[2,7],[0],[0],[2,7,8]],"metadata":{"editor_version":"2.20.0","game":"BlossomBlastSaga","level_hash":"b872bffc6a96c53fadf5c42d059cc20b"},"properties":{"game_mode":"SPRING_CLEANING","is_hard":false,"nr_colors":"3","nr_moves":"29","random_seed":"0","star_1":"8000","star_2":"16000","star_3":"24000","tutorial_ids":""},"tiles":[{"exclude_color":"2","max_start_strength":"2","min_start_strength":"1","type":"bud_spawner"},{"type":"normal_slot"},{"health":"3","location":"west","type":"wall","wall_type":"fence"},{"exclude_color":"2","max_start_strength":"3","min_start_strength":"1","type":"bud_spawner"},{"health":"3","location":"east","type":"wall","wall_type":"fence"},{"health":"3","location":"south","type":"wall","wall_type":"fence"},{"health":"2","type":"weed"},{"size":"1","type":"pile_of_leaves"},{"type":"water_lily_leaf"},{"type":"water_lily_leaf_spawner"},{"type":"water_slot"},{"direction":"left","health":"3","type":"crow"},{"direction":"right","health":"3","type":"crow"},{"direction":"up","health":"3","type":"crow"},{"color":"4","type":"exploding_mushroom"}]}