{"level":[[0],[0],[0],[1],[1,2,3],[1],[0],[0],[0],[0],[1,2],[0],[0],[1,3],[0],[0],[1,2],[0],[5,4,6],[5,6,7],[0],[1,3],[1,3],[1,3],[0],[5,8,7],[5,9],[0],[0],[5,6,7],[5,6,7],[1,3],[5,8,7],[5,8,7],[0],[0],[1,2],[5,6,7,10],[1,11,3],[1,11,3],[5,8,7],[1,11,3],[1,11,3],[5,12,7,10],[1,2],[1],[5,13,7,10],[5,12,7,10],[5,14,8,7],[5,14,6,7],[5,14,15,7],[5,6,7,10],[5,13,7,10],[1],[1],[0],[1,16],[5,14,13,7],[1],[5,14,6,7],[1,16],[0],[1],[0],[5,14,8,7],[5,14,8,7],[5],[1],[5],[5,14,6,7],[5,14,6,7],[0],[5,17,8],[0],[0],[5],[1],[5],[0],[0],[5,18],[0],[5],[5],[1,19],[1],[1,19],[5],[5],[0]],"metadata":{"editor_version":"2.20.0","game":"BlossomBlastSaga","level_hash":"d0cdeade5176f8ee7bbed36e8363ee7d"},"properties":{"game_mode":"COLLECT_FLOWERS","goal_1":"red_12","goal_2":"pink_12","goal_3":"blue_12","is_hard":true,"nr_colors":"4","nr_moves":"19","random_seed":"0","star_1":"8000","star_2":"23500","star_3":"39000","tutorial_ids":""},"tiles":[{"type":"normal_slot"},{"exclude_color":"2","max_start_strength":"3","min_start_strength":"1","type":"bud_spawner"},{"health":"3","type":"green_house"},{"skin":"water","teleport_id":"2","type":"teleport_out"},{"type":"water_slot"},{"direction":"se","type":"stream"},{"type":"floating_log"},{"direction":"ne","type":"stream"},{"skin":"water","teleport_id":"2","type":"teleport_in"},{"health":"2","type":"rolling_stone"},{"health":"2","type":"falling_pot"},{"direction":"sw","type":"stream"},{"direction":"n","type":"stream"},{"direction":"up","health":"3","type":"crow"},{"direction":"s","type":"stream"},{"health":"3","type":"falling_pot"},{"skin":"water","teleport_id":"1","type":"teleport_out"},{"skin":"water","teleport_id":"1","type":"teleport_in"},{"animate_at_creation":"0","health":"3","type":"molehill"}]}