{"level":[[1,2],[1],[1,2],[1],[3],[1],[1,4],[1],[1,4],[1],[1,5],[1],[1,5],[1],[1,5],[1],[1,5],[1],[1],[1],[1,5],[1],[1,6],[1],[1,5],[1],[1],[1],[1],[1],[1,7],[1],[1,7],[1],[1],[1],[1,8],[1,10,7,9],[1,7,9],[1,11],[1,12,7,9,13],[1,11],[1,7,13],[1,10,7,13],[1,8],[1,14,7,9],[1],[1],[1],[1,15],[1],[1],[1],[1,14,7,13],[1],[1,5],[1],[1],[1,16],[1],[1],[1,5],[1],[1],[1],[1,5],[1,5],[1,17],[1,5],[1,5],[1],[1],[1,18],[1,19],[1],[1],[1,16],[1],[1],[1,19],[1,20],[1,21],[3],[1],[1],[1,15],[1],[1],[3],[1,22]],"metadata":{"editor_version":"2.20.0","game":"BlossomBlastSaga","level_hash":"6ba613787853f73d6092eff844a2179a"},"properties":{"game_mode":"REMOVE_ALL_BIG_BUDS","is_hard":false,"nr_colors":"3","nr_moves":"15","random_seed":"0","star_1":"8000","star_2":"48500","star_3":"89000","tutorial_ids":""},"tiles":[{"type":"normal_slot"},{"teleport_id":"2","type":"teleport_land_out"},{"type":"water_slot"},{"teleport_id":"1","type":"teleport_land_out"},{"health":"3","type":"green_house"},{"color":"1","max_strength":"30","type":"big_bud"},{"location":"south","type":"wall","wall_type":"wall"},{"color":"2","max_strength":"25","type":"big_bud"},{"location":"east","type":"wall","wall_type":"wall"},{"animate_at_creation":"0","health":"1","type":"molehill"},{"exclude_color":"4","max_start_strength":"3","min_start_strength":"1","type":"bud_spawner"},{"color":"1","max_strength":"25","type":"big_bud"},{"location":"west","type":"wall","wall_type":"wall"},{"color":"3","max_strength":"30","type":"big_bud"},{"color":"3","max_strength":"18","type":"big_bud"},{"color":"2","max_strength":"18","type":"big_bud"},{"color":"1","max_strength":"18","type":"big_bud"},{"color":"3","max_strength":"15","type":"big_bud"},{"color":"1","max_strength":"15","type":"big_bud"},{"color":"2","max_strength":"15","type":"big_bud"},{"teleport_id":"1","type":"teleport_land_in"},{"teleport_id":"2","type":"teleport_land_in"}]}