{"level":[[0],[2,1],[0],[2,1],[0],[2],[2,1],[2],[2,1],[2],[2],[2],[2],[2],[2],[2],[2,3],[2,4],[2],[8,5,7,6],[2],[2],[2],[8,5,7,9],[2],[2],[8,11,10,12],[8,10,7,3,13],[2,14,3,12],[8,15,7,12,13],[2,14],[8,10,7,9,3],[2,14,3,12],[8,15,7,12,6],[2,14],[8,10,7,6],[8,10,7,3,6],[2,16,3,12],[8,17,7,12,6],[2,16],[8,10,7,3,13],[2,16,3,12],[8,17,7,12,13],[2,16],[8,10,7,13],[8,10,7,3,13],[2,14,3,12],[8,17,7,12,13],[2,14],[8,10,7,3,13],[2,14,3,12],[8,17,7,12,6],[2,14],[8,10,7,6],[8,10,7,6],[8,18,19,12],[8,17,7,6],[8,15,7,9],[8,5,7,9],[8,18,19],[8,17,7,13],[8,15,7,6],[8,5,7,13],[8,20,4,3],[8,18,19],[8,18,19],[8,18,19],[8,18,19],[8,18,19,21],[8,18,19],[8,18,19,21],[8,18,19],[8,18,19,21],[2,22,23],[8,18,19,21],[2,23],[2,22],[2,16],[2,22,23],[2,16],[2,23],[2,16],[0],[2,16],[0],[0],[0],[0],[0],[0]],"metadata":{"editor_version":"2.19.5","game":"BlossomBlastSaga","level_hash":"1bc1b601526b1972c1d6c83ac71ac9cc","tracking_id":28754203},"properties":{"game_mode":"SPRING_CLEANING","is_hard":false,"nr_colors":"4","nr_moves":"19","random_seed":"0","star_1":"8000","star_2":"33690","star_3":"45350","tutorial_ids":""},"tiles":[{"max_start_strength":"4","min_start_strength":"1","type":"bud_spawner"},{"type":"normal_slot"},{"location":"east","type":"wall","wall_type":"wall"},{"location":"south","type":"wall","wall_type":"wall"},{"direction":"sw","type":"stream"},{"size":"1","type":"pile_of_leaves"},{"type":"floating_log"},{"type":"water_slot"},{"type":"exploding_mushroom"},{"direction":"s","type":"stream"},{"skin":"water","teleport_id":"1","type":"teleport_out"},{"location":"west","type":"wall","wall_type":"wall"},{"health":"3","type":"slime"},{"health":"2","type":"weed"},{"direction":"nw","type":"stream"},{"health":"3","type":"weed"},{"direction":"n","type":"stream"},{"type":"water_lily_leaf"},{"type":"water_lily_leaf_spawner"},{"teleport_id":"1","type":"teleport_in"},{"health":"3","location":"south","type":"wall","wall_type":"fence"},{"health":"3","location":"east","type":"wall","wall_type":"fence"},{"health":"3","location":"west","type":"wall","wall_type":"fence"}]}