{"level":[[2,1],[2],[0],[2,3],[2,4,3],[2,3],[0],[2],[2,1],[2],[2],[2,5],[2,3],[7,6,8,3],[2,3],[2,5],[2],[2],[2],[2],[2,9],[2,9],[7,6,8,3],[2,9],[2,9],[2],[2],[2],[2],[7,6,8,10],[7,6,8,10],[2,9],[7,6,8,10],[7,6,8,10],[2],[2],[2],[2],[2,11],[2,12],[2,10],[2,13],[2,11],[2],[2],[2],[2],[2,11],[2,12],[7,6,8,10],[2,13],[2,11],[2],[2],[2],[2],[2,11],[2,11],[7,6,8,10],[2,11],[2,11],[2],[2],[2],[2],[2,10],[2,10],[2,11],[2,10],[2,10],[2],[2],[2,13],[2,13],[2],[2,10],[2,11],[2,10],[2],[2,12],[2,12],[0],[0],[2,13],[0],[0],[0],[2,12],[0],[0]],"metadata":{"editor_version":"2.20.0","game":"BlossomBlastSaga","level_hash":"4cb3bcdcc6db55b9d964e3b7d186e044"},"properties":{"game_mode":"COLLECT_FLOWERS","goal_1":"blue_4","goal_2":"pink_4","goal_3":"orange_4","goal_4":"red_4","is_hard":false,"nr_colors":"4","nr_moves":"19","random_seed":"0","star_1":"8000","star_2":"21000","star_3":"39000","tutorial_ids":""},"tiles":[{"exclude_color":"2","max_start_strength":"2","min_start_strength":"1","type":"bud_spawner"},{"type":"normal_slot"},{"health":"3","type":"falling_pot"},{"exclude_color":"1","exclude_color2":"4","max_start_strength":"2","min_start_strength":"1","type":"bud_spawner"},{"health":"3","type":"pot"},{"type":"water_lily_leaf"},{"type":"water_slot"},{"type":"water_lily_leaf_spawner"},{"direction":"up","health":"3","type":"crow"},{"health":"1","type":"pot"},{"health":"2","type":"pot"},{"direction":"left","health":"3","type":"crow"},{"direction":"right","health":"3","type":"crow"}]}