{"level":[[2,1],[2,3],[6,5,3,4],[2,4],[2,1],[2,3],[6,7,3,4],[2,4],[2,1],[2],[2,3],[6,8,9,3,4],[2,4],[2],[2,3],[6,8,9,3,4],[2,4],[2],[2],[2,3],[6,8,9,3,4],[2,4],[2],[2,3],[6,8,9,3,4],[2,4],[2],[2],[2,3],[6,8,9,10,3,4],[2,4,11],[2],[2,3,11],[6,8,9,10,3,4],[2,4],[2],[2],[2,3],[6,8,9,3,4],[2,4,11],[2],[2,3,11],[6,8,9,3,4],[2,4],[2],[2],[2,3],[6,8,9,10,3,4],[2,4,11],[2],[2,3,11],[6,8,9,10,3,4],[2,4],[2],[2,13,12],[2,13,3,14],[6,8,9,3,4],[2,4],[2],[2,3],[6,8,9,3,4],[2,13,15,4],[2,13,12],[2,16,15],[6,17,18,3],[6,8,9,10,3,4],[2,4],[2],[2,3],[6,8,9,10,3,4],[6,20,19,4],[2,21,14],[6,19,9,22],[6,19,9,10,22,4],[6,8,9,3,4],[2,4],[2],[2,3],[6,8,9,3,4],[6,18,9,22,3],[6,18,9,22,3],[0],[0],[6,8,9,22,3,4],[2,23],[2],[2,23],[6,8,9,10,22,3,4],[0],[0]],"metadata":{"editor_version":"2.20.0","game":"BlossomBlastSaga","level_hash":"2a2267d41d6df0a48547128fb6c6957e"},"properties":{"game_mode":"COLLECT_FLOWERS","goal_1":"pink_12","goal_2":"blue_11","goal_3":"orange_10","goal_4":"red_9","is_hard":false,"nr_colors":"4","nr_moves":"16","random_seed":"0","star_1":"8000","star_2":"26000","star_3":"44000","tutorial_ids":""},"tiles":[{"exclude_color":"4","exclude_color2":"2","max_start_strength":"2","min_start_strength":"1","type":"bud_spawner"},{"type":"normal_slot"},{"health":"3","location":"east","type":"wall","wall_type":"fence"},{"health":"3","location":"west","type":"wall","wall_type":"fence"},{"skin":"water","teleport_id":"2","type":"teleport_in"},{"type":"water_slot"},{"skin":"water","teleport_id":"1","type":"teleport_in"},{"direction":"n","type":"stream"},{"type":"floating_log"},{"health":"1","type":"pot"},{"size":"1","type":"pile_of_leaves"},{"location":"south","type":"wall","wall_type":"wall"},{"direction":"up","health":"3","type":"crow"},{"location":"west","type":"wall","wall_type":"wall"},{"location":"east","type":"wall","wall_type":"wall"},{"color":"4","max_start_strength":"2","min_start_strength":"1","type":"bud_spawner"},{"skin":"water","teleport_id":"2","type":"teleport_out"},{"direction":"sw","type":"stream"},{"direction":"se","type":"stream"},{"skin":"water","teleport_id":"1","type":"teleport_out"},{"color":"2","max_start_strength":"2","min_start_strength":"1","type":"bud_spawner"},{"health":"3","location":"south","type":"wall","wall_type":"fence"},{"type":"snail"}]}